pyephember2/__init__.py
pyephember2/pyephember2.py
pyephember2-0.4.11.dist-info/licenses/LICENSE.txt
pyephember2-0.4.11.dist-info/METADATA
pyephember2-0.4.11.dist-info/WHEEL
pyephember2-0.4.11.dist-info/top_level.txt
pyephember2-0.4.11.dist-info/RECORD
