Metadata-Version: 2.4
Name: pyephember2
Version: 0.4.11
Summary: Python library to work with ember from EPH Controls
Home-page: https://github.com/roberty99/pyephember2
Download-URL: https://github.com/roberty99/pyephember2/archive/0.4.3.tar.gz
Author: Robert Young
Author-email: youngro@tcd.ie
License: MIT
Keywords: ephember
Platform: any
License-File: LICENSE.txt
Requires-Dist: requests
Requires-Dist: paho-mqtt
Dynamic: author
Dynamic: author-email
Dynamic: download-url
Dynamic: home-page
Dynamic: keywords
Dynamic: license
Dynamic: license-file
Dynamic: platform
Dynamic: requires-dist
Dynamic: summary
